{
    "Atlanta Hawks" : ["#e03a3e", "#ffffff"],
    "Boston Celtics" : ["#007a33", "#ba9653"],
    "Brooklyn Nets" : ["#777d84", "#000000"],
    "Charlotte Hornets" : ["#00788c", "#1d1160"],
    "Chicago Bulls" : ["#ce1141", "#000000"],
    "Cleveland Cavaliers" : ["#860038", "#fdbb30"],
    "Dallas Mavericks" : ["#002b5e", "#b8c4ca"],
    "Denver Nuggets" : ["#0e2240", "#fec524"],
    "Detroit Pistons" : ["#1d42ba", "#ffffff"],
    "Golden State Warriors" : ["#ffc72c", "#1d428a"],
    "Houston Rockets" : ["#ce1141", "#ffffff"],
    "Indiana Pacers" : ["#fdbb30", "#002d62"],
    "Los Angeles Clippers" : ["#c8102e", "#ffffff"],
    "Los Angeles Lakers" : ["#f9a01b", "#552583"],
    "Memphis Grizzlies" : ["#5d76a9", "#12173f"],
    "Miami Heat" : ["#98002e", "#f9a01b"],
    "Milwaukee Bucks" : ["#00471b", "#eee1c6"],
    "Minnesota Timberwolves" : ["#236192", "#0c2340"],
    "New Orleans Pelicans" : ["#c8102e", "#0c2340"],
    "New York Knicks" : ["#006bb6", "#f58426"],
    "Oklahoma City Thunder" : ["#007ac1", "#ffffff"],
    "Orlando Magic" : ["#0077c0", "#c4ced4"],
    "Philadelphia 76ers" : ["#006bb6", "#ffffff"],
    "Phoenix Suns" : ["#e56020", "#1d1160"],
    "Portland Trail Blazers" : ["#e03a3e", "#ffffff"],
    "Sacramento Kings" : ["#5a2d81", "#63727a"],
    "San Antonio Spurs" : ["#c4ced4", "#000000"],
    "Toronto Raptors" : ["#ce1141", "#ffffff"],
    "Utah Jazz" : ["#f9a01b", "#000000"],
    "Washington Wizards" : ["#e31837", "#002b5c"]
}